mapctf/__init__.py
mapctf/base.py
mapctf-1.0.dist-info/METADATA
mapctf-1.0.dist-info/RECORD
mapctf-1.0.dist-info/WHEEL
mapctf-1.0.dist-info/top_level.txt
