Metadata-Version: 2.1
Name: mapctf
Version: 1.0
Summary: map coordinate transform betweem google and baidu
Home-page: UNKNOWN
Author: YK
Author-email: 
License: UNKNOWN
Platform: UNKNOWN
Classifier: Programming Language :: Python :: 3
Classifier: License :: OSI Approved :: MIT License
Classifier: Operating System :: OS Independent
